adaptdl/__init__.py
adaptdl/_signal.py
adaptdl/checkpoint.py
adaptdl/checkpoint_test.py
adaptdl/collective.py
adaptdl/collective_test.py
adaptdl/conftest.py
adaptdl/env.py
adaptdl/fit_test.py
adaptdl/goodput.py
adaptdl/goodput_test.py
adaptdl/reducer.py
adaptdl/reducer_test.py
adaptdl/sched_hints.py
adaptdl/torch/__init__.py
adaptdl/torch/_metrics.py
adaptdl/torch/_metrics_test.py
adaptdl/torch/accumulator.py
adaptdl/torch/accumulator_test.py
adaptdl/torch/data.py
adaptdl/torch/data_test.py
adaptdl/torch/epoch.py
adaptdl/torch/epoch_test.py
adaptdl/torch/gradient_noise_scale.py
adaptdl/torch/gradient_noise_scale_test.py
adaptdl/torch/iterator.py
adaptdl/torch/parallel.py
adaptdl/torch/parallel_test.py
adaptdl/torch/scaling_rules.py
adaptdl/torch/scaling_rules_test.py
adaptdl_modified_pandyaka-1.0.2.dist-info/LICENSE
adaptdl_modified_pandyaka-1.0.2.dist-info/METADATA
adaptdl_modified_pandyaka-1.0.2.dist-info/WHEEL
adaptdl_modified_pandyaka-1.0.2.dist-info/top_level.txt
adaptdl_modified_pandyaka-1.0.2.dist-info/RECORD
