Metadata-Version: 2.1
Name: adaptdl-modified-pandyaka
Version: 1.0.2
Summary: Dynamic-resource trainer and scheduler for deep learning
Home-page: https://github.com/pandyakaa/modified-adaptdl
Author: Petuum Inc. & The AdaptDL Authors, modified by pandyakaa
Author-email: aurick.qiao@petuum.com, pandyaka.aptanagi@gmail.com
License: UNKNOWN
Platform: UNKNOWN
Classifier: Programming Language :: Python :: 3
Classifier: License :: Other/Proprietary License
Classifier: Operating System :: POSIX :: Linux
Requires-Python: >=3.6
Requires-Dist: autograd (>=1.3)
Requires-Dist: pandas (>=0.24.2)
Requires-Dist: portpicker (>=1.3.1)
Requires-Dist: redis (>=3.3.8)
Requires-Dist: scipy (>=1.3.0)
Requires-Dist: semver (>=2.13.0)
